xjfx.py
xjfx-1.1.0.dist-info/METADATA
xjfx-1.1.0.dist-info/WHEEL
xjfx-1.1.0.dist-info/top_level.txt
xjfx-1.1.0.dist-info/RECORD
